[
    {
        "inputs": [
            {
                "internalType": "contract IFrankencoin",
                "name": "zchf_",
                "type": "address"
            }
        ],
        "stateMutability": "nonpayable",
        "type": "constructor"
    },
    {
        "inputs": [
            {
                "internalType": "contract TestToken",
                "name": "col",
                "type": "address"
            },
            {
                "internalType": "contract MintingHub",
                "name": "hub",
                "type": "address"
            }
        ],
        "name": "initiatePosition",
        "outputs": [
            {
                "internalType": "address",
                "name": "",
                "type": "address"
            }
        ],
        "stateMutability": "nonpayable",
        "type": "function"
    },
    {
        "inputs": [
            {
                "internalType": "address",
                "name": "pos",
                "type": "address"
            },
            {
                "internalType": "uint256",
                "name": "amount",
                "type": "uint256"
            }
        ],
        "name": "mint",
        "outputs": [],
        "stateMutability": "nonpayable",
        "type": "function"
    },
    {
        "inputs": [
            {
                "internalType": "contract StablecoinBridge",
                "name": "bridge",
                "type": "address"
            },
            {
                "internalType": "uint256",
                "name": "amount",
                "type": "uint256"
            }
        ],
        "name": "obtainFrankencoins",
        "outputs": [],
        "stateMutability": "nonpayable",
        "type": "function"
    }
]
